[
  {
    "sensR_function": "betaBin",
    "sensR_file": "R/betaBin.R",
    "senspy_module": "senspy.models",
    "senspy_function": "BetaBinomial",
    "description": "Fits a beta-binomial model to overdispersed binomial data."
  },
  {
    "sensR_function": "discrim",
    "sensR_file": "R/discrim.R",
    "senspy_module": "senspy.discrimination",
    "senspy_function": "discrim",
    "description": "General function for d-prime estimation from various discrimination methods (e.g., 2AFC, Triangle, Duo-Trio)."
  },
  {
    "sensR_function": "twoAC",
    "sensR_file": "R/twoAC.R",
    "senspy_module": "senspy.discrimination",
    "senspy_function": "twoAC",
    "description": "Thurstonian model for 2-Alternative Choice (Yes/No) tasks, estimating sensitivity (delta) and bias (tau)."
  },
  {
    "sensR_function": "dod",
    "sensR_file": "R/dod.R",
    "senspy_module": "senspy.discrimination",
    "senspy_function": "dod",
    "description": "Degree of Difference (DoD) analysis, estimating d-prime and boundary parameters (tau)."
  },
  {
    "sensR_function": "samediff",
    "sensR_file": "R/samediff.R",
    "senspy_module": "senspy.discrimination",
    "senspy_function": "samediff",
    "description": "Same-Different method analysis, estimating sensitivity (delta) and criterion (tau)."
  },
  {
    "sensR_function": "dprime_test",
    "sensR_file": "R/dprime_test.R",
    "senspy_module": "senspy.discrimination",
    "senspy_function": "dprime_test",
    "description": "Tests a d-prime value against a hypothesized value, possibly for multiple groups."
  },
  {
    "sensR_function": "dprime_compare",
    "sensR_file": "R/dprime_compare.R",
    "senspy_module": "senspy.discrimination",
    "senspy_function": "dprime_compare",
    "description": "Compares d-prime values from multiple groups to test for equality."
  },
  {
    "sensR_function": "SDT",
    "sensR_file": "R/ROC.R",
    "senspy_module": "senspy.discrimination",
    "senspy_function": "SDT",
    "description": "Signal Detection Theory analysis for rating scales, calculating z(Hit rate), z(False alarm rate), and d-prime for each criterion."
  },
  {
    "sensR_function": "AUC",
    "sensR_file": "R/ROC.R",
    "senspy_module": "senspy.discrimination",
    "senspy_function": "AUC",
    "description": "Calculates the Area Under the ROC Curve (AUC) from d-prime."
  },
  {
    "sensR_function": "psyfun",
    "sensR_file": "R/links.R", 
    "senspy_module": "senspy.links",
    "senspy_function": "psyfun",
    "description": "Maps d-prime to proportion correct for various discrimination methods."
  },
  {
    "sensR_function": "psyinv",
    "sensR_file": "R/links.R",
    "senspy_module": "senspy.links",
    "senspy_function": "psyinv",
    "description": "Maps proportion correct to d-prime for various discrimination methods."
  },
  {
    "sensR_function": "psyderiv",
    "sensR_file": "R/links.R",
    "senspy_module": "senspy.links",
    "senspy_function": "psyderiv",
    "description": "Calculates the derivative of the psychometric function (psyfun) with respect to d-prime."
  },
  {
    "sensR_function": "rescale",
    "sensR_file": "R/links.R",
    "senspy_module": "senspy.links",
    "senspy_function": "rescale",
    "description": "Rescales values between proportion correct (pc), proportion discriminated (pd), and d-prime (dp) scales, optionally transforming standard errors."
  },
  {
    "sensR_function": "getPguess",
    "sensR_file": "R/utils.R", 
    "senspy_module": "senspy.discrimination", 
    "senspy_function": "get_pguess",
    "description": "Returns the chance performance (pguess) for a given discrimination method."
  },
  {
    "sensR_function": "pc2pd",
    "sensR_file": "R/utils.R",
    "senspy_module": "senspy.discrimination",
    "senspy_function": "pc2pd",
    "description": "Converts proportion correct (pc) to proportion discriminated (pd)."
  },
  {
    "sensR_function": "pd2pc",
    "sensR_file": "R/utils.R",
    "senspy_module": "senspy.discrimination",
    "senspy_function": "pd2pc",
    "description": "Converts proportion discriminated (pd) to proportion correct (pc)."
  }
]
